{"i": {"Q103738": "Gotlannin l\u00e4\u00e4ni", "Q498857": "Kristianstadin kunta", "Q214829": "It\u00e4-G\u00f6tanmaa", "Q103732": "Taalainmaan l\u00e4\u00e4ni", "Q508108": "Motalan kunta", "Q105075": "V\u00e4stmanlandin l\u00e4\u00e4ni", "Q533915": "Malm\u00f6husin l\u00e4\u00e4ni", "Q504994": "Sundsvallin kunta", "Q103659": "Sk\u00e5nen l\u00e4\u00e4ni", "Q15304552": "", "Q103691": "Hallandin l\u00e4\u00e4ni", "Q103679": "J\u00e4mtlandin l\u00e4\u00e4ni", "Q221990": "Sollefte\u00e5n kunta", "Q180756": "Sk\u00e5ne", "Q103699": "G\u00e4vleborgin l\u00e4\u00e4ni", "Q103672": "J\u00f6nk\u00f6pingin l\u00e4\u00e4ni", "Q2714126": "", "Q339637": "Kristianstadin l\u00e4\u00e4ni", "Q103093": "L\u00e4nsi-G\u00f6tanmaan l\u00e4\u00e4ni", "Q205218": "Taalainmaa", "Q515299": "Kindan kunta", "Q15981396": "", "Q505064": "Trosan kunta", "Q675653": "Blekinge", "Q239332": "Gnestan kunta", "Q104257": "\u00d6rebron l\u00e4\u00e4ni", "Q50631": "Tromssan l\u00e4\u00e4ni", "Q626045": "Halland", "Q500267": "Nyk\u00f6pingin kunta", "Q209853": "\u00c5ngermanland", "Q103707": "Kalmarin l\u00e4\u00e4ni", "Q113718": "Botkyrkan kunta", "Q514815": "Kramforsin kunta", "Q213551": "L\u00e4nsi-G\u00f6tanmaa", "Q106915": "S\u00f6dermanlandin l\u00e4\u00e4ni", "Q102377": "Blekingen l\u00e4\u00e4ni", "Q203509": "Uplanti", "Q199957": "Sm\u00e5land", "Q104940": "It\u00e4-G\u00f6tanmaan l\u00e4\u00e4ni", "Q103686": "Norrbottenin l\u00e4\u00e4ni", "Q212640": "Lappi", "Q516336": "S\u00f6dert\u00e4ljen kunta", "Q922842": "Skaraborgin l\u00e4\u00e4ni", "Q1255130": "Salemin kunta", "Q104231": "Tukholman l\u00e4\u00e4ni", "Q321430": "V\u00e4stmanland", "Q515969": "Vadstenan kunta", "Q104746": "Kronobergin l\u00e4\u00e4ni", "Q10709206": "", "Q104891": "V\u00e4sternorrlandin l\u00e4\u00e4ni", "Q106789": "V\u00e4rmlannin l\u00e4\u00e4ni", "Q104926": "Uppsalan l\u00e4\u00e4ni", "Q104877": "V\u00e4sterbottenin l\u00e4\u00e4ni"}}